{
    "swagger": "2.0",
    "info": {
        "description": "API for Medical Record Management System",
        "title": "Medical Record API",
        "contact": {},
        "version": "1.0"
    },
    "host": "localhost:3000",
    "basePath": "/",
    "paths": {
        "/api/appointments": {
            "get": {
                "security": [
                    {
                        "BearerAuth": []
                    }
                ],
                "produces": [
                    "application/json"
                ],
                "tags": [
                    "Appointments"
                ],
                "summary": "Get all appointments",
                "responses": {
                    "200": {
                        "description": "OK",
                        "schema": {
                            "$ref": "#/definitions/utils.Response"
                        }
                    }
                }
            },
            "post": {
                "security": [
                    {
                        "BearerAuth": []
                    }
                ],
                "consumes": [
                    "application/json"
                ],
                "produces": [
                    "application/json"
                ],
                "tags": [
                    "Appointments"
                ],
                "summary": "Create appointment",
                "parameters": [
                    {
                        "description": "Appointment Request",
                        "name": "request",
                        "in": "body",
                        "required": true,
                        "schema": {
                            "$ref": "#/definitions/dto.CreateAppointmentRequest"
                        }
                    }
                ],
                "responses": {
                    "201": {
                        "description": "Created",
                        "schema": {
                            "$ref": "#/definitions/utils.Response"
                        }
                    }
                }
            }
        },
        "/api/appointments/doctor/{doctorId}": {
            "get": {
                "security": [
                    {
                        "BearerAuth": []
                    }
                ],
                "produces": [
                    "application/json"
                ],
                "tags": [
                    "Appointments"
                ],
                "summary": "Get appointments by doctor",
                "parameters": [
                    {
                        "type": "string",
                        "description": "Doctor ID",
                        "name": "doctorId",
                        "in": "path",
                        "required": true
                    }
                ],
                "responses": {
                    "200": {
                        "description": "OK",
                        "schema": {
                            "$ref": "#/definitions/utils.Response"
                        }
                    }
                }
            }
        },
        "/api/appointments/{id}/status": {
            "patch": {
                "security": [
                    {
                        "BearerAuth": []
                    }
                ],
                "consumes": [
                    "application/json"
                ],
                "produces": [
                    "application/json"
                ],
                "tags": [
                    "Appointments"
                ],
                "summary": "Update appointment status",
                "parameters": [
                    {
                        "type": "string",
                        "description": "Appointment ID",
                        "name": "id",
                        "in": "path",
                        "required": true
                    },
                    {
                        "description": "Status Request",
                        "name": "request",
                        "in": "body",
                        "required": true,
                        "schema": {
                            "$ref": "#/definitions/dto.UpdateAppointmentStatusRequest"
                        }
                    }
                ],
                "responses": {
                    "200": {
                        "description": "OK",
                        "schema": {
                            "$ref": "#/definitions/utils.Response"
                        }
                    }
                }
            }
        },
        "/api/auth/login/doctor": {
            "post": {
                "consumes": [
                    "application/json"
                ],
                "produces": [
                    "application/json"
                ],
                "tags": [
                    "Auth"
                ],
                "summary": "Doctor login",
                "parameters": [
                    {
                        "description": "Login Request",
                        "name": "request",
                        "in": "body",
                        "required": true,
                        "schema": {
                            "$ref": "#/definitions/dto.LoginRequest"
                        }
                    }
                ],
                "responses": {
                    "200": {
                        "description": "OK",
                        "schema": {
                            "$ref": "#/definitions/utils.Response"
                        }
                    }
                }
            }
        },
        "/api/auth/login/patient": {
            "post": {
                "consumes": [
                    "application/json"
                ],
                "produces": [
                    "application/json"
                ],
                "tags": [
                    "Auth"
                ],
                "summary": "Patient login",
                "parameters": [
                    {
                        "description": "Login Request",
                        "name": "request",
                        "in": "body",
                        "required": true,
                        "schema": {
                            "$ref": "#/definitions/dto.LoginRequest"
                        }
                    }
                ],
                "responses": {
                    "200": {
                        "description": "OK",
                        "schema": {
                            "$ref": "#/definitions/utils.Response"
                        }
                    }
                }
            }
        },
        "/api/auth/register": {
            "post": {
                "consumes": [
                    "application/json"
                ],
                "produces": [
                    "application/json"
                ],
                "tags": [
                    "Auth"
                ],
                "summary": "Register new patient",
                "parameters": [
                    {
                        "description": "Register Request",
                        "name": "request",
                        "in": "body",
                        "required": true,
                        "schema": {
                            "$ref": "#/definitions/dto.RegisterPatientRequest"
                        }
                    }
                ],
                "responses": {
                    "201": {
                        "description": "Created",
                        "schema": {
                            "$ref": "#/definitions/utils.Response"
                        }
                    }
                }
            }
        },
        "/api/medical-records": {
            "get": {
                "security": [
                    {
                        "BearerAuth": []
                    }
                ],
                "produces": [
                    "application/json"
                ],
                "tags": [
                    "Medical Records"
                ],
                "summary": "Get all medical records",
                "responses": {
                    "200": {
                        "description": "OK",
                        "schema": {
                            "$ref": "#/definitions/utils.Response"
                        }
                    }
                }
            },
            "post": {
                "security": [
                    {
                        "BearerAuth": []
                    }
                ],
                "consumes": [
                    "application/json"
                ],
                "produces": [
                    "application/json"
                ],
                "tags": [
                    "Medical Records"
                ],
                "summary": "Create medical record",
                "parameters": [
                    {
                        "description": "Medical Record Request",
                        "name": "request",
                        "in": "body",
                        "required": true,
                        "schema": {
                            "$ref": "#/definitions/dto.CreateMedicalRecordRequest"
                        }
                    }
                ],
                "responses": {
                    "201": {
                        "description": "Created",
                        "schema": {
                            "$ref": "#/definitions/utils.Response"
                        }
                    }
                }
            }
        },
        "/api/medical-records/patient/{patientId}": {
            "get": {
                "security": [
                    {
                        "BearerAuth": []
                    }
                ],
                "produces": [
                    "application/json"
                ],
                "tags": [
                    "Medical Records"
                ],
                "summary": "Get medical records by patient",
                "parameters": [
                    {
                        "type": "string",
                        "description": "Patient ID",
                        "name": "patientId",
                        "in": "path",
                        "required": true
                    }
                ],
                "responses": {
                    "200": {
                        "description": "OK",
                        "schema": {
                            "$ref": "#/definitions/utils.Response"
                        }
                    }
                }
            }
        },
        "/api/medical-records/report/monthly": {
            "get": {
                "security": [
                    {
                        "BearerAuth": []
                    }
                ],
                "produces": [
                    "application/json"
                ],
                "tags": [
                    "Medical Records"
                ],
                "summary": "Get monthly report",
                "parameters": [
                    {
                        "type": "string",
                        "description": "Month (YYYY-MM)",
                        "name": "month",
                        "in": "query",
                        "required": true
                    }
                ],
                "responses": {
                    "200": {
                        "description": "OK",
                        "schema": {
                            "$ref": "#/definitions/utils.Response"
                        }
                    }
                }
            }
        },
        "/api/patients": {
            "get": {
                "security": [
                    {
                        "BearerAuth": []
                    }
                ],
                "produces": [
                    "application/json"
                ],
                "tags": [
                    "Patients"
                ],
                "summary": "Get all patients",
                "responses": {
                    "200": {
                        "description": "OK",
                        "schema": {
                            "$ref": "#/definitions/utils.Response"
                        }
                    }
                }
            }
        },
        "/api/patients/{id}": {
            "get": {
                "security": [
                    {
                        "BearerAuth": []
                    }
                ],
                "produces": [
                    "application/json"
                ],
                "tags": [
                    "Patients"
                ],
                "summary": "Get patient by ID",
                "parameters": [
                    {
                        "type": "string",
                        "description": "Patient ID",
                        "name": "id",
                        "in": "path",
                        "required": true
                    }
                ],
                "responses": {
                    "200": {
                        "description": "OK",
                        "schema": {
                            "$ref": "#/definitions/utils.Response"
                        }
                    }
                }
            }
        }
    },
    "definitions": {
        "dto.CreateAppointmentRequest": {
            "type": "object",
            "required": [
                "complaint",
                "date",
                "doctor_id",
                "patient_id",
                "poli",
                "time"
            ],
            "properties": {
                "complaint": {
                    "type": "string"
                },
                "date": {
                    "type": "string"
                },
                "doctor_id": {
                    "type": "string"
                },
                "patient_id": {
                    "type": "string"
                },
                "poli": {
                    "type": "string"
                },
                "time": {
                    "type": "string"
                }
            }
        },
        "dto.CreateMedicalRecordRequest": {
            "type": "object",
            "required": [
                "anamnesa",
                "appointment_id",
                "diagnosis",
                "objective",
                "patient_id",
                "prescription",
                "therapy"
            ],
            "properties": {
                "anamnesa": {
                    "type": "string"
                },
                "appointment_id": {
                    "type": "string"
                },
                "diagnosis": {
                    "type": "string"
                },
                "next_visit": {
                    "type": "string"
                },
                "objective": {
                    "type": "string"
                },
                "patient_id": {
                    "type": "string"
                },
                "prescription": {
                    "type": "string"
                },
                "therapy": {
                    "type": "string"
                }
            }
        },
        "dto.LoginRequest": {
            "type": "object",
            "required": [
                "email",
                "password"
            ],
            "properties": {
                "email": {
                    "type": "string"
                },
                "password": {
                    "type": "string"
                }
            }
        },
        "dto.RegisterPatientRequest": {
            "type": "object",
            "required": [
                "email",
                "name",
                "password"
            ],
            "properties": {
                "address": {
                    "type": "string"
                },
                "blood_type": {
                    "type": "string"
                },
                "date_of_birth": {
                    "type": "string"
                },
                "email": {
                    "type": "string"
                },
                "gender": {
                    "type": "string"
                },
                "name": {
                    "type": "string"
                },
                "password": {
                    "type": "string",
                    "minLength": 6
                },
                "phone": {
                    "type": "string"
                }
            }
        },
        "dto.UpdateAppointmentStatusRequest": {
            "type": "object",
            "required": [
                "status"
            ],
            "properties": {
                "status": {
                    "type": "string",
                    "enum": [
                        "approved",
                        "rejected"
                    ]
                }
            }
        },
        "utils.Response": {
            "type": "object",
            "properties": {
                "data": {},
                "message": {
                    "type": "string"
                },
                "success": {
                    "type": "boolean"
                }
            }
        }
    },
    "securityDefinitions": {
        "BearerAuth": {
            "type": "apiKey",
            "name": "Authorization",
            "in": "header"
        }
    }
}